ros2_graphs_mermaid/__init__.py
ros2_graphs_mermaid/__main__.py
ros2_graphs_mermaid/graph_generator.py
ros2_graphs_mermaid-0.0.1.dist-info/LICENSE
ros2_graphs_mermaid-0.0.1.dist-info/METADATA
ros2_graphs_mermaid-0.0.1.dist-info/WHEEL
ros2_graphs_mermaid-0.0.1.dist-info/top_level.txt
ros2_graphs_mermaid-0.0.1.dist-info/RECORD
