Metadata-Version: 2.1
Name: ros2_graphs_mermaid
Version: 0.0.1
Summary: Generate mermaid description of ROS2 graphs to add on your markdown files.
Home-page: https://github.com/kiwicampus/ros2_graphs_mermaid
License-File: LICENSE
